{"authType":"EMAILPASSWD","bans":[],"country":"ID","createdAt":"2024-05-02T07:21:16.659132Z","dateOfBirth":"1991-01-01T00:00:00Z","displayName":"Load Test User 1714634476403 2289455","deletionStatus":false,"emailVerified":true,"enabled":true,"lastDateOfBirthChangedTime":"0001-01-01T00:00:00Z","lastEnabledChangedTime":"0001-01-01T00:00:00Z","emailAddress":"stg-hosting-user-393@example.com","namespace":"performancetest","namespaceRoles":[{"roleId":"2251438839e948d783ec0e5281daf05b","namespace":"*"}],"oldEmailAddress":"stg-hosting-user-393@example.com","permissions":[],"phoneVerified":false,"roles":["2251438839e948d783ec0e5281daf05b"],"userId":"39beae67e1a84b77a20d0112423c5afb","userName":"loadtestuser17146344764032289455"}
